.gitignore
LICENSE
README.md
pyproject.toml
setup.cfg
setup.py
.github/FUNDING.yml
.github/workflows/publish-to-test-pypy.yml
src/heare/client/__init__.py
src/heare/client/events/__init__.py
src/heare/client/events/message.py
src/heare/client/events/ws.py
src/heare/logging/__init__.py
src/heare/skills/__init__.py
src/heare/skills/container.py
src/heare/skills/intent/__init__.py
src/heare/skills/intent/adapt.py
src/heare_sdk.egg-info/PKG-INFO
src/heare_sdk.egg-info/SOURCES.txt
src/heare_sdk.egg-info/dependency_links.txt
src/heare_sdk.egg-info/requires.txt
src/heare_sdk.egg-info/top_level.txt