Metadata-Version: 2.1
Name: heare-sdk
Version: 0.0.9
Summary: Software Development Kit for Heare.io applications.
Home-page: https://github.com/heare-io/heare-sdk
Author: Sean Fitzgerald
Author-email: seanfitz@heare.io
License: UNKNOWN
Project-URL: Bug Tracker, https://github.com/heare-io/heare-sdk/issues
Platform: UNKNOWN
Classifier: Programming Language :: Python :: 3
Classifier: License :: OSI Approved :: GNU Lesser General Public License v3 (LGPLv3)
Classifier: Operating System :: OS Independent
Requires-Python: >=3.6
License-File: LICENSE
